{
    "format_version": 3,
    "format_uuid": "289f771f-2c9a-4d73-9f3f-8492495a924d",
    "tooth": "github.com/engsr6982/PLand",
    "version": "0.18.1",
    "info": {
        "name": "PLand",
        "description": "基于 LeviLamina 的领地系统 / A land system based on LeviLamina",
        "tags": [
            "type:mod",
            "platform:levilamina",
            "land",
            "pland"
        ],
        "avatar_url": ""
    },
    "variants": [
        {
            "platform": "win-x64",
            "dependencies": {
                "github.com/LiteLDev/LeviLamina": "1.9.*",
                "github.com/MiracleForest/iListenAttentively-Release": "0.11.*"
            },
            "assets": [
                {
                    "type": "zip",
                    "urls": [
                        "https://{{tooth}}/releases/download/v{{version}}/PLand-windows-x64.zip"
                    ],
                    "placements": [
                        {
                            "type": "dir",
                            "src": "PLand/",
                            "dest": "plugins/PLand"
                        }
                    ]
                }
            ]
        }
    ]
}
